{
  "variants": {
    "flipped=true,powered=false,facing=north": {
      "model": "railroads:block/switch_rail_turn_left_off"
    },
    "flipped=true,powered=false,facing=south": {
      "model": "railroads:block/switch_rail_turn_left_off",
      "y": 180
    },
    "flipped=true,powered=false,facing=east": {
      "model": "railroads:block/switch_rail_turn_left_off",
      "y": 90
    },
    "flipped=true,powered=false,facing=west": {
      "model": "railroads:block/switch_rail_turn_left_off",
      "y": 270
    },
    "flipped=true,powered=true,facing=north": {
      "model": "railroads:block/switch_rail_turn_left_on"
    },
    "flipped=true,powered=true,facing=south": {
      "model": "railroads:block/switch_rail_turn_left_on",
      "y": 180
    },
    "flipped=true,powered=true,facing=east": {
      "model": "railroads:block/switch_rail_turn_left_on",
      "y": 90
    },
    "flipped=true,powered=true,facing=west": {
      "model": "railroads:block/switch_rail_turn_left_on",
      "y": 270
    },

    "flipped=false,powered=false,facing=north": {
      "model": "railroads:block/switch_rail_turn_right_off"
    },
    "flipped=false,powered=false,facing=south": {
      "model": "railroads:block/switch_rail_turn_right_off",
      "y": 180
    },
    "flipped=false,powered=false,facing=east": {
      "model": "railroads:block/switch_rail_turn_right_off",
      "y": 90
    },
    "flipped=false,powered=false,facing=west": {
      "model": "railroads:block/switch_rail_turn_right_off",
      "y": 270
    },
    "flipped=false,powered=true,facing=north": {
      "model": "railroads:block/switch_rail_turn_right_on"
    },
    "flipped=false,powered=true,facing=south": {
      "model": "railroads:block/switch_rail_turn_right_on",
      "y": 180
    },
    "flipped=false,powered=true,facing=east": {
      "model": "railroads:block/switch_rail_turn_right_on",
      "y": 90
    },
    "flipped=false,powered=true,facing=west": {
      "model": "railroads:block/switch_rail_turn_right_on",
      "y": 270
    }
  }
}
